README.md
setup.cfg
setup.py
wpcraft/__init__.py
wpcraft/types.py
wpcraft/wpcraft.py
wpcraft.egg-info/PKG-INFO
wpcraft.egg-info/SOURCES.txt
wpcraft.egg-info/dependency_links.txt
wpcraft.egg-info/entry_points.txt
wpcraft.egg-info/requires.txt
wpcraft.egg-info/top_level.txt
wpcraft/utils/__init__.py
wpcraft/utils/utils.py
wpcraft/wpcraftaccess/__init__.py
wpcraft/wpcraftaccess/wpcraftaccess.py