Metadata-Version: 2.1
Name: wpcraft
Version: 1.2.3
Summary: A CLI for fetching wallpapers from WallpapersCraft
Home-page: https://github.com/rafalcieslak/wpcraft
Author: Rafał Cieślak
Author-email: rafalcieslak256@gmail.com
License: UNKNOWN
Keywords: cli wallpaper desktop
Platform: UNKNOWN
Classifier: Development Status :: 5 - Production/Stable
Classifier: Environment :: Console
Classifier: Intended Audience :: End Users/Desktop
Classifier: License :: OSI Approved :: GNU General Public License v3 (GPLv3)
Classifier: Natural Language :: English
Classifier: Programming Language :: Python :: 3
Classifier: Programming Language :: Python :: 3.6
Classifier: Topic :: Desktop Environment
Classifier: Topic :: Utilities
Requires-Python: >=3.6
